fitting2d/__init__.py
fitting2d-1.0.0a5.dist-info/LICENSE
fitting2d-1.0.0a5.dist-info/METADATA
fitting2d-1.0.0a5.dist-info/WHEEL
fitting2d-1.0.0a5.dist-info/entry_points.txt
fitting2d-1.0.0a5.dist-info/top_level.txt
fitting2d-1.0.0a5.dist-info/RECORD
