Metadata-Version: 2.1
Name: fitting2d
Version: 1.0.0a5
Summary: a library for performing two-dimensional curve-fitting
Home-page: https://fitting2d.readthedocs.io/en/latest/
Author: Keisuke Sehara
Author-email: keisuke.sehara@gmail.com
License: MIT
Platform: UNKNOWN
Classifier: Development Status :: 3 - Alpha
Classifier: License :: OSI Approved :: MIT License
Classifier: Programming Language :: Python :: 3
Classifier: Operating System :: OS Independent
Requires-Dist: scipy
Requires-Dist: numpy
